dr_packager/__init__.py
dr_packager/__main__.py
dr_packager/dr_packager.py
dr_packager-0.1.0.dist-info/entry_points.txt
dr_packager-0.1.0.dist-info/WHEEL
dr_packager-0.1.0.dist-info/METADATA
dr_packager-0.1.0.dist-info/RECORD
