Metadata-Version: 2.1
Name: dr-packager
Version: 0.1.0
Summary: Automate react shipping with Django with a simple command
License: MIT
Author: moporem
Author-email: pooriavrj@gmail.com
Requires-Python: >=3.8
Classifier: License :: OSI Approved :: MIT License
Classifier: Programming Language :: Python :: 3
Classifier: Programming Language :: Python :: 3.10
Classifier: Programming Language :: Python :: 3.8
Classifier: Programming Language :: Python :: 3.9
